Workbook

Sheet README
A1: ConsolFlora data import template | B1: Version 1.0, October 2026
A3: How to use | B3: Fill one sheet per kind of data, save as .xlsx, then upload it on the Import page. The app checks every row first (dry run) and shows errors before anything is saved.
A4: Required columns | B4: Dark red headers with * must be filled. Green headers are optional.
A5: Your input cells | B5: Pale yellow cells. Row 2 on each sheet is an EXAMPLE row in blue text: overwrite or delete it before importing.
A6: Calculated cells | B6: Pale green cells are formulas. Leave them alone; the app recalculates them on import anyway.
A7: Dropdowns | B7: Columns such as currency, incoterm and payment terms only accept values from the Lists sheet.
A8: Codes link sheets | B8: farm_code, customer_code, product_code and box_code must match exactly across sheets (case-sensitive).
A9: Updating records | B9: A row whose code already exists updates that record; a new code creates one. Nothing is deleted by import: set active = N instead.
A10: Import order | B10: Lists > Farms > Customers > BoxTypes > Products > PackRates > PriceList > FreightRates > PackingList.
A11: Box numbers | B11: PackingList numbers boxes 1..N per shipment_ref in row order. SSCC numbers are never in this file; the app issues them.
A12: Dates | B12: Use YYYY-MM-DD.
A13: Personal data | B13: Only business contact details. No ID numbers, dates of birth or personal addresses.
A14: Placeholder data | B14: All example names, numbers and prices are made up. Box dimensions are examples; measure your own.
A16: Colour key
B17: Required column header
B18: Optional column header
B19: Input cell
B20: Calculated cell

Sheet Farms
A1: farm_code * | B1: farm_name * | C1: country * | D1: region | E1: address | F1: gln | G1: kra_pin | H1: sales_agent_name * | I1: sales_agent_email * | J1: sales_agent_phone | K1: currency * | L1: payment_terms * | M1: active *
A2: KIBO | B2: Kibo Roses Ltd | C2: Kenya | D2: Nakuru | E2: PO Box 0000, Nakuru | G2: P000000000A | H2: Ann Wanjiru | I2: ann@kiboroses.co.ke | J2: +254711000000 | K2: USD | L2: Net 15 | M2: Y
A3: NAKU | B3: Naku Flowers | C3: Kenya | D3: Naivasha | F3: 8712345678906 | H3: Ben Otieno | I3: ben@naku.co.ke | K3: USD | L3: Net 7 | M3: Y

Sheet Customers
A1: customer_code * | B1: company_name * | C1: country * | D1: city | E1: delivery_address | F1: gln | G1: vat_or_tax_id | H1: contact_name * | I1: contact_email * | J1: contact_phone | K1: currency * | L1: incoterm * | M1: payment_terms * | N1: credit_limit | O1: destination_airport * | P1: language | Q1: active *
A2: FDAMS | B2: Example Flowers BV | C2: Netherlands | D2: Aalsmeer | E2: Example street 1, Aalsmeer | G2: NL000000000B01 | H2: Piet Example | I2: buying@exampleflowers.nl | J2: +31600000000 | K2: EUR | L2: CPT | M2: Net 15 | N2: 20000 | O2: AMS | P2: EN | Q2: Y

Sheet Products
A1: product_code * | B1: flower_type * | C1: variety * | D1: colour | E1: floricode_product_id | F1: vbn_code | G1: grade * | H1: stem_length_cm * | I1: head_size_cm | J1: maturity | K1: stems_per_bunch * | L1: default_farm_code | M1: active *
A2: ROS-RN-A1-70 | B2: Rose | C2: Red Naomi | D2: Red | G2: A1 | H2: 70 | I2: 5.5 | J2: Stage 2 | K2: 10 | L2: KIBO | M2: Y

Sheet BoxTypes
A1: box_code * | B1: description | C1: length_cm * | D1: width_cm * | E1: height_cm * | F1: tare_weight_kg | G1: volumetric_kg | H1: vbn_packaging_code | I1: active *
A2: QB | B2: Quarter box | C2: 100 | D2: 25 | E2: 15 | F2: 1.2 | G2: =IF(AND(ISNUMBER(C2),ISNUMBER(D2),ISNUMBER(E2)),ROUND(C2*D2*E2/6000,2),"") | I2: Y
G3: =IF(AND(ISNUMBER(C3),ISNUMBER(D3),ISNUMBER(E3)),ROUND(C3*D3*E3/6000,2),"")
G4: =IF(AND(ISNUMBER(C4),ISNUMBER(D4),ISNUMBER(E4)),ROUND(C4*D4*E4/6000,2),"")
G5: =IF(AND(ISNUMBER(C5),ISNUMBER(D5),ISNUMBER(E5)),ROUND(C5*D5*E5/6000,2),"")
G6: =IF(AND(ISNUMBER(C6),ISNUMBER(D6),ISNUMBER(E6)),ROUND(C6*D6*E6/6000,2),"")
G7: =IF(AND(ISNUMBER(C7),ISNUMBER(D7),ISNUMBER(E7)),ROUND(C7*D7*E7/6000,2),"")
G8: =IF(AND(ISNUMBER(C8),ISNUMBER(D8),ISNUMBER(E8)),ROUND(C8*D8*E8/6000,2),"")
G9: =IF(AND(ISNUMBER(C9),ISNUMBER(D9),ISNUMBER(E9)),ROUND(C9*D9*E9/6000,2),"")
G10: =IF(AND(ISNUMBER(C10),ISNUMBER(D10),ISNUMBER(E10)),ROUND(C10*D10*E10/6000,2),"")
G11: =IF(AND(ISNUMBER(C11),ISNUMBER(D11),ISNUMBER(E11)),ROUND(C11*D11*E11/6000,2),"")
G12: =IF(AND(ISNUMBER(C12),ISNUMBER(D12),ISNUMBER(E12)),ROUND(C12*D12*E12/6000,2),"")
G13: =IF(AND(ISNUMBER(C13),ISNUMBER(D13),ISNUMBER(E13)),ROUND(C13*D13*E13/6000,2),"")
G14: =IF(AND(ISNUMBER(C14),ISNUMBER(D14),ISNUMBER(E14)),ROUND(C14*D14*E14/6000,2),"")
... G500: =IF(AND(ISNUMBER(C500),ISNUMBER(D500),ISNUMBER(E500)),ROUND(C500*D500*E500/6000,2),"")

Sheet PackRates
A1: product_code * | B1: box_code * | C1: bunches_per_box * | D1: stems_per_box | E1: est_gross_weight_kg
A2: ROS-RN-A1-70 | B2: QB | C2: 8 | D2: =IFERROR(C2*INDEX(Products!$K:$K,MATCH(A2,Products!$A:$A,0)),"") | E2: 9.5
D3: =IFERROR(C3*INDEX(Products!$K:$K,MATCH(A3,Products!$A:$A,0)),"")
D4: =IFERROR(C4*INDEX(Products!$K:$K,MATCH(A4,Products!$A:$A,0)),"")
D5: =IFERROR(C5*INDEX(Products!$K:$K,MATCH(A5,Products!$A:$A,0)),"")
D6: =IFERROR(C6*INDEX(Products!$K:$K,MATCH(A6,Products!$A:$A,0)),"")
D7: =IFERROR(C7*INDEX(Products!$K:$K,MATCH(A7,Products!$A:$A,0)),"")
D8: =IFERROR(C8*INDEX(Products!$K:$K,MATCH(A8,Products!$A:$A,0)),"")
D9: =IFERROR(C9*INDEX(Products!$K:$K,MATCH(A9,Products!$A:$A,0)),"")
D10: =IFERROR(C10*INDEX(Products!$K:$K,MATCH(A10,Products!$A:$A,0)),"")
D11: =IFERROR(C11*INDEX(Products!$K:$K,MATCH(A11,Products!$A:$A,0)),"")
D12: =IFERROR(C12*INDEX(Products!$K:$K,MATCH(A12,Products!$A:$A,0)),"")
D13: =IFERROR(C13*INDEX(Products!$K:$K,MATCH(A13,Products!$A:$A,0)),"")
D14: =IFERROR(C14*INDEX(Products!$K:$K,MATCH(A14,Products!$A:$A,0)),"")
... D500: =IFERROR(C500*INDEX(Products!$K:$K,MATCH(A500,Products!$A:$A,0)),"")

Sheet PriceList
A1: farm_code * | B1: product_code * | C1: currency * | D1: price_per_stem * | E1: valid_from * | F1: valid_to | G1: min_order_stems
A2: SIAN | B2: ROS-RN-A1-70 | C2: USD | D2: 0.25 | E2: 46296 | F2: 46387

Sheet FreightRates
A1: origin_airport * | B1: destination_airport * | C1: airline_or_agent | D1: currency * | E1: rate_per_kg * | F1: min_charge | G1: weight_break_kg | H1: valid_from * | I1: valid_to
A2: NBO | B2: AMS | C2: Example Airline | D2: USD | E2: 3.1 | F2: 150 | G2: 100 | H2: 46296

Sheet PackingList
A1: shipment_ref * | B1: awb | C1: hawb | D1: customer_code * | E1: farm_code * | F1: po_number | G1: product_code * | H1: box_code * | I1: boxes * | J1: bunches_per_box | K1: total_stems | L1: box_from | M1: box_to | N1: shipment_total_boxes | O1: notes
A2: SHP-2026-0001 | B2: 706-00000000 | D2: FDAMS | E2: SIAN | F2: PO-2026-0001 | G2: ROS-RN-A1-70 | H2: QB | I2: 12 | J2: =IF(G2="","",IFERROR(INDEX(PackRates!$C:$C,MATCH(1,INDEX((PackRates!$A$1:$A$500=G2)*(PackRates!$B$1:$B$500=H2),0),0)),"")) | K2: =IF(OR(I2="",J2=""),"",IFERROR(I2*J2*INDEX(Products!$K:$K,MATCH(G2,Products!$A:$A,0)),"")) | L2: =IF(A2="","",1) | M2: =IF(OR(L2="",I2=""),"",L2+I2-1) | N2: =IF(A2="","",SUMIF($A$2:$A$500,A2,$I$2:$I$500))
J3: =IF(G3="","",IFERROR(INDEX(PackRates!$C:$C,MATCH(1,INDEX((PackRates!$A$1:$A$500=G3)*(PackRates!$B$1:$B$500=H3),0),0)),"")) | K3: =IF(OR(I3="",J3=""),"",IFERROR(I3*J3*INDEX(Products!$K:$K,MATCH(G3,Products!$A:$A,0)),"")) | L3: =IF(A3="","",IF(A3=A2,M2+1,1)) | M3: =IF(OR(L3="",I3=""),"",L3+I3-1) | N3: =IF(A3="","",SUMIF($A$2:$A$500,A3,$I$2:$I$500))
J4: =IF(G4="","",IFERROR(INDEX(PackRates!$C:$C,MATCH(1,INDEX((PackRates!$A$1:$A$500=G4)*(PackRates!$B$1:$B$500=H4),0),0)),"")) | K4: =IF(OR(I4="",J4=""),"",IFERROR(I4*J4*INDEX(Products!$K:$K,MATCH(G4,Products!$A:$A,0)),"")) | L4: =IF(A4="","",IF(A4=A3,M3+1,1)) | M4: =IF(OR(L4="",I4=""),"",L4+I4-1) | N4: =IF(A4="","",SUMIF($A$2:$A$500,A4,$I$2:$I$500))
J5: =IF(G5="","",IFERROR(INDEX(PackRates!$C:$C,MATCH(1,INDEX((PackRates!$A$1:$A$500=G5)*(PackRates!$B$1:$B$500=H5),0),0)),"")) | K5: =IF(OR(I5="",J5=""),"",IFERROR(I5*J5*INDEX(Products!$K:$K,MATCH(G5,Products!$A:$A,0)),"")) | L5: =IF(A5="","",IF(A5=A4,M4+1,1)) | M5: =IF(OR(L5="",I5=""),"",L5+I5-1) | N5: =IF(A5="","",SUMIF($A$2:$A$500,A5,$I$2:$I$500))
J6: =IF(G6="","",IFERROR(INDEX(PackRates!$C:$C,MATCH(1,INDEX((PackRates!$A$1:$A$500=G6)*(PackRates!$B$1:$B$500=H6),0),0)),"")) | K6: =IF(OR(I6="",J6=""),"",IFERROR(I6*J6*INDEX(Products!$K:$K,MATCH(G6,Products!$A:$A,0)),"")) | L6: =IF(A6="","",IF(A6=A5,M5+1,1)) | M6: =IF(OR(L6="",I6=""),"",L6+I6-1) | N6: =IF(A6="","",SUMIF($A$2:$A$500,A6,$I$2:$I$500))
J7: =IF(G7="","",IFERROR(INDEX(PackRates!$C:$C,MATCH(1,INDEX((PackRates!$A$1:$A$500=G7)*(PackRates!$B$1:$B$500=H7),0),0)),"")) | K7: =IF(OR(I7="",J7=""),"",IFERROR(I7*J7*INDEX(Products!$K:$K,MATCH(G7,Products!$A:$A,0)),"")) | L7: =IF(A7="","",IF(A7=A6,M6+1,1)) | M7: =IF(OR(L7="",I7=""),"",L7+I7-1) | N7: =IF(A7="","",SUMIF($A$2:$A$500,A7,$I$2:$I$500))
J8: =IF(G8="","",IFERROR(INDEX(PackRates!$C:$C,MATCH(1,INDEX((PackRates!$A$1:$A$500=G8)*(PackRates!$B$1:$B$500=H8),0),0)),"")) | K8: =IF(OR(I8="",J8=""),"",IFERROR(I8*J8*INDEX(Products!$K:$K,MATCH(G8,Products!$A:$A,0)),"")) | L8: =IF(A8="","",IF(A8=A7,M7+1,1)) | M8: =IF(OR(L8="",I8=""),"",L8+I8-1) | N8: =IF(A8="","",SUMIF($A$2:$A$500,A8,$I$2:$I$500))
J9: =IF(G9="","",IFERROR(INDEX(PackRates!$C:$C,MATCH(1,INDEX((PackRates!$A$1:$A$500=G9)*(PackRates!$B$1:$B$500=H9),0),0)),"")) | K9: =IF(OR(I9="",J9=""),"",IFERROR(I9*J9*INDEX(Products!$K:$K,MATCH(G9,Products!$A:$A,0)),"")) | L9: =IF(A9="","",IF(A9=A8,M8+1,1)) | M9: =IF(OR(L9="",I9=""),"",L9+I9-1) | N9: =IF(A9="","",SUMIF($A$2:$A$500,A9,$I$2:$I$500))
J10: =IF(G10="","",IFERROR(INDEX(PackRates!$C:$C,MATCH(1,INDEX((PackRates!$A$1:$A$500=G10)*(PackRates!$B$1:$B$500=H10),0),0)),"")) | K10: =IF(OR(I10="",J10=""),"",IFERROR(I10*J10*INDEX(Products!$K:$K,MATCH(G10,Products!$A:$A,0)),"")) | L10: =IF(A10="","",IF(A10=A9,M9+1,1)) | M10: =IF(OR(L10="",I10=""),"",L10+I10-1) | N10: =IF(A10="","",SUMIF($A$2:$A$500,A10,$I$2:$I$500))
J11: =IF(G11="","",IFERROR(INDEX(PackRates!$C:$C,MATCH(1,INDEX((PackRates!$A$1:$A$500=G11)*(PackRates!$B$1:$B$500=H11),0),0)),"")) | K11: =IF(OR(I11="",J11=""),"",IFERROR(I11*J11*INDEX(Products!$K:$K,MATCH(G11,Products!$A:$A,0)),"")) | L11: =IF(A11="","",IF(A11=A10,M10+1,1)) | M11: =IF(OR(L11="",I11=""),"",L11+I11-1) | N11: =IF(A11="","",SUMIF($A$2:$A$500,A11,$I$2:$I$500))
J12: =IF(G12="","",IFERROR(INDEX(PackRates!$C:$C,MATCH(1,INDEX((PackRates!$A$1:$A$500=G12)*(PackRates!$B$1:$B$500=H12),0),0)),"")) | K12: =IF(OR(I12="",J12=""),"",IFERROR(I12*J12*INDEX(Products!$K:$K,MATCH(G12,Products!$A:$A,0)),"")) | L12: =IF(A12="","",IF(A12=A11,M11+1,1)) | M12: =IF(OR(L12="",I12=""),"",L12+I12-1) | N12: =IF(A12="","",SUMIF($A$2:$A$500,A12,$I$2:$I$500))
J13: =IF(G13="","",IFERROR(INDEX(PackRates!$C:$C,MATCH(1,INDEX((PackRates!$A$1:$A$500=G13)*(PackRates!$B$1:$B$500=H13),0),0)),"")) | K13: =IF(OR(I13="",J13=""),"",IFERROR(I13*J13*INDEX(Products!$K:$K,MATCH(G13,Products!$A:$A,0)),"")) | L13: =IF(A13="","",IF(A13=A12,M12+1,1)) | M13: =IF(OR(L13="",I13=""),"",L13+I13-1) | N13: =IF(A13="","",SUMIF($A$2:$A$500,A13,$I$2:$I$500))
J14: =IF(G14="","",IFERROR(INDEX(PackRates!$C:$C,MATCH(1,INDEX((PackRates!$A$1:$A$500=G14)*(PackRates!$B$1:$B$500=H14),0),0)),"")) | K14: =IF(OR(I14="",J14=""),"",IFERROR(I14*J14*INDEX(Products!$K:$K,MATCH(G14,Products!$A:$A,0)),"")) | L14: =IF(A14="","",IF(A14=A13,M13+1,1)) | M14: =IF(OR(L14="",I14=""),"",L14+I14-1) | N14: =IF(A14="","",SUMIF($A$2:$A$500,A14,$I$2:$I$500))
... J500: =IF(G500="","",IFERROR(INDEX(PackRates!$C:$C,MATCH(1,INDEX((PackRates!$A$1:$A$500=G500)*(PackRates!$B$1:$B$500=H500),0),0)),"")) | K500: =IF(OR(I500="",J500=""),"",IFERROR(I500*J500*INDEX(Products!$K:$K,MATCH(G500,Products!$A:$A,0)),"")) | L500: =IF(A500="","",IF(A500=A499,M499+1,1)) | M500: =IF(OR(L500="",I500=""),"",L500+I500-1) | N500: =IF(A500="","",SUMIF($A$2:$A$500,A500,$I$2:$I$500))

Sheet Lists
A1: Currency | B1: Incoterm | C1: PaymentTerms | D1: YesNo | E1: Language | F1: Maturity | G1: Country
A2: KES | B2: FCA | C2: Prepaid | D2: Y | E2: EN | F2: Stage 1 | G2: Kenya
A3: USD | B3: CPT | C3: Net 7 | D3: N | E3: NL | F3: Stage 2 | G3: Netherlands
A4: EUR | B4: CIP | C4: Net 15 | F4: Stage 3 | G4: United Kingdom
B5: DAP | C5: Net 30 | F5: Stage 4 | G5: Germany
B6: DPU | G6: Russia
B7: DDP | G7: United Arab Emirates
B8: EXW | G8: Japan
G9: Australia
G10: United States
G11: Other
A12: Edit these lists to change the dropdowns. Incoterms 2020: FOB, CFR and CIF are sea-freight terms, so air shipments use FCA, CPT, CIP or DAP.
